<?xml version="1.0" encoding="UTF-8" standalone="yes" ?>
<form shortcuts="true">
	<test name="testform" action="{url->(/)}" method="post">
		<input type="text" placeholder="{lang->(testform.firstname)}"  name="firstname" autocomplete="off">
			<validation>
				<options blank="true"></options>
				<errors>
					<blank>asdasdasd {lang->(testform.lastname)} {lang->(testform.lastname)} {lang->(testform.lastname)} asdasda</blank>
				</errors>
			</validation>
		</input>
		<input type="submit" name="test-submit" value="Test" />
	</test>
</form>